plumage_dash_components/Dropdown.py
plumage_dash_components/Select.py
plumage_dash_components/__init__.py
plumage_dash_components/_imports_.py
plumage_dash_components/metadata.json
plumage_dash_components/package.json
plumage_dash_components/plumage_dash_components.css
plumage_dash_components/plumage_dash_components.dev.js
plumage_dash_components/plumage_dash_components.min.js
plumage_dash_components-0.0.1.dist-info/LICENSE
plumage_dash_components-0.0.1.dist-info/METADATA
plumage_dash_components-0.0.1.dist-info/WHEEL
plumage_dash_components-0.0.1.dist-info/top_level.txt
plumage_dash_components-0.0.1.dist-info/RECORD
