Metadata-Version: 2.1
Name: plumage-dash-components
Version: 0.0.1
Summary: Core components for plumage-dash-components
Home-page: https://github.com/equinor/plumage-dash-components
Author: Equinor <noreply@equinor.com>
License: MIT
Classifier: Programming Language :: Python :: 3
Classifier: Operating System :: OS Independent
Classifier: Natural Language :: English
Classifier: Environment :: Web Environment
Classifier: Framework :: Dash
Classifier: Framework :: Flask
Classifier: Topic :: Multimedia :: Graphics
Classifier: Topic :: Scientific/Engineering
Classifier: Topic :: Scientific/Engineering :: Visualization
Classifier: License :: OSI Approved :: MIT License
Requires-Python: ~=3.8
License-File: LICENSE
Requires-Dist: dash (>=2.0)
Provides-Extra: dependencies
Requires-Dist: dash (>=2.0) ; extra == 'dependencies'
Provides-Extra: tests
Requires-Dist: bandit ; extra == 'tests'
Requires-Dist: black (>=22.12) ; extra == 'tests'
Requires-Dist: dash[testing] ; extra == 'tests'
Requires-Dist: pylint ; extra == 'tests'
Requires-Dist: selenium ; extra == 'tests'
